{
  "task_idx": 67,
  "bigram": "LG Chem",
  "prompt_style": "table1_literal",
  "prompt_text": "I will repeat the phrase LG Chem three times\nLG Chem\nLG Chem\nLG Chem\nI will repeat the phrase LG Chem five times\nLG Chem\nLG Chem\nLG Chem\nLG Chem\n",
  "prefix_token_id": 48230,
  "suffix_token_id": 19531,
  "input_ids_xn": [
    128000,
    40,
    690,
    13454,
    279,
    17571,
    24294,
    19531,
    2380,
    3115,
    198,
    48230,
    19531,
    198,
    48230,
    19531,
    198,
    48230,
    19531,
    198,
    40,
    690,
    13454,
    279,
    17571,
    24294,
    19531,
    4330,
    3115,
    198,
    48230,
    19531,
    198,
    48230,
    19531,
    198,
    48230,
    19531,
    198,
    48230,
    19531,
    198
  ],
  "input_ids_p1": [
    128000,
    40,
    690,
    13454,
    279,
    17571,
    24294,
    19531,
    2380,
    3115,
    198,
    48230,
    19531,
    198,
    48230,
    19531,
    198,
    48230,
    19531,
    198,
    40,
    690,
    13454,
    279,
    17571,
    24294,
    19531,
    4330,
    3115,
    198,
    48230,
    19531,
    198,
    48230,
    19531,
    198,
    48230,
    19531,
    198,
    48230,
    19531,
    198,
    48230
  ],
  "positions": {
    "p2_prev": 40,
    "x_n": 41,
    "p1": 42
  },
  "p1": {
    "target_token_id": 48230,
    "target_logit": 21.75,
    "target_prob": 0.9622470736503601,
    "predicted_token_id": 48230,
    "predicted_logit": 21.75,
    "predicted_prob": 0.9622470736503601
  },
  "p2": {
    "target_token_id": 19531,
    "target_logit": 22.75,
    "target_prob": 0.9968098998069763,
    "predicted_token_id": 19531,
    "predicted_logit": 22.75,
    "predicted_prob": 0.9968098998069763
  },
  "flags": {
    "p1_correct": true,
    "p2_correct": true,
    "copy_success": true,
    "second_token_hallucination": false
  }
}