{
  "task_idx": 4,
  "bigram": "controller.controller",
  "prompt_style": "table1_literal",
  "prompt_text": "I will repeat the phrase controller.controller three times\ncontroller.controller\ncontroller.controller\ncontroller.controller\nI will repeat the phrase controller.controller five times\ncontroller.controller\ncontroller.controller\ncontroller.controller\ncontroller.controller\n",
  "prefix_token_id": 7299,
  "suffix_token_id": 14854,
  "input_ids_xn": [
    128000,
    40,
    690,
    13454,
    279,
    17571,
    6597,
    14854,
    2380,
    3115,
    198,
    7299,
    14854,
    198,
    7299,
    14854,
    198,
    7299,
    14854,
    198,
    40,
    690,
    13454,
    279,
    17571,
    6597,
    14854,
    4330,
    3115,
    198,
    7299,
    14854,
    198,
    7299,
    14854,
    198,
    7299,
    14854,
    198,
    7299,
    14854,
    198
  ],
  "input_ids_p1": [
    128000,
    40,
    690,
    13454,
    279,
    17571,
    6597,
    14854,
    2380,
    3115,
    198,
    7299,
    14854,
    198,
    7299,
    14854,
    198,
    7299,
    14854,
    198,
    40,
    690,
    13454,
    279,
    17571,
    6597,
    14854,
    4330,
    3115,
    198,
    7299,
    14854,
    198,
    7299,
    14854,
    198,
    7299,
    14854,
    198,
    7299,
    14854,
    198,
    7299
  ],
  "positions": {
    "p2_prev": 40,
    "x_n": 41,
    "p1": 42
  },
  "p1": {
    "target_token_id": 7299,
    "target_logit": 23.625,
    "target_prob": 0.9612175226211548,
    "predicted_token_id": 7299,
    "predicted_logit": 23.625,
    "predicted_prob": 0.9612175226211548
  },
  "p2": {
    "target_token_id": 14854,
    "target_logit": 24.75,
    "target_prob": 0.9992343187332153,
    "predicted_token_id": 14854,
    "predicted_logit": 24.75,
    "predicted_prob": 0.9992343187332153
  },
  "flags": {
    "p1_correct": true,
    "p2_correct": true,
    "copy_success": true,
    "second_token_hallucination": false
  }
}